<?xml version="1.0" encoding="utf-8"?>
<odoo>
    <data noupdate="0">

        <!-- ========== 启蒙 ========== -->

        <record id="selector_hanzi_2026" model="learn.selector">
            <field name="category_id" ref="dim_category_enlightenment"/>
            <field name="subject_id" ref="dim_subject_hanzi"/>
            <field name="year_id" ref="dim_year_2026"/>
            <field name="sequence">10</field>
        </record>
        <record id="selector_hanzi_2025" model="learn.selector">
            <field name="category_id" ref="dim_category_enlightenment"/>
            <field name="subject_id" ref="dim_subject_hanzi"/>
            <field name="year_id" ref="dim_year_2025"/>
            <field name="sequence">20</field>
        </record>
        <record id="selector_hanzi_2024" model="learn.selector">
            <field name="category_id" ref="dim_category_enlightenment"/>
            <field name="subject_id" ref="dim_subject_hanzi"/>
            <field name="year_id" ref="dim_year_2024"/>
            <field name="sequence">30</field>
        </record>
        <record id="selector_mathfun_2025" model="learn.selector">
            <field name="category_id" ref="dim_category_enlightenment"/>
            <field name="subject_id" ref="dim_subject_math_fun"/>
            <field name="year_id" ref="dim_year_2025"/>
            <field name="sequence">40</field>
        </record>
        <record id="selector_mathfun_2024" model="learn.selector">
            <field name="category_id" ref="dim_category_enlightenment"/>
            <field name="subject_id" ref="dim_subject_math_fun"/>
            <field name="year_id" ref="dim_year_2024"/>
            <field name="sequence">50</field>
        </record>

        <!-- ========== 中小学 ========== -->

        <!-- 小学 一年级 语文 2026 人教版 下册 -->
        <record id="selector_g1_chinese_pep_down" model="learn.selector">
            <field name="category_id" ref="dim_category_nine_year"/>
            <field name="stage_id" ref="dim_stage_primary"/>
            <field name="class_id" ref="dim_class_grade_1"/>
            <field name="subject_id" ref="dim_subject_chinese"/>
            <field name="year_id" ref="dim_year_2026"/>
            <field name="version_id" ref="dim_version_pep"/>
            <field name="semester_id" ref="dim_semester_down"/>
            <field name="sequence">10</field>
        </record>
        <!-- 小学 一年级 数学 2026 人教版 下册 -->
        <record id="selector_g1_math_pep_down" model="learn.selector">
            <field name="category_id" ref="dim_category_nine_year"/>
            <field name="stage_id" ref="dim_stage_primary"/>
            <field name="class_id" ref="dim_class_grade_1"/>
            <field name="subject_id" ref="dim_subject_math"/>
            <field name="year_id" ref="dim_year_2026"/>
            <field name="version_id" ref="dim_version_pep"/>
            <field name="semester_id" ref="dim_semester_down"/>
            <field name="sequence">20</field>
        </record>
        <!-- 小学 五年级 英语 2026 湘少版 下册 -->
        <record id="selector_g5_english_hunan_down" model="learn.selector">
            <field name="category_id" ref="dim_category_nine_year"/>
            <field name="stage_id" ref="dim_stage_primary"/>
            <field name="class_id" ref="dim_class_grade_5"/>
            <field name="subject_id" ref="dim_subject_english"/>
            <field name="year_id" ref="dim_year_2026"/>
            <field name="version_id" ref="dim_version_hunan"/>
            <field name="semester_id" ref="dim_semester_down"/>
            <field name="sequence">30</field>
        </record>
        <!-- 小学 五年级 语文 2026 人教版 下册 -->
        <record id="selector_g5_chinese_pep_down" model="learn.selector">
            <field name="category_id" ref="dim_category_nine_year"/>
            <field name="stage_id" ref="dim_stage_primary"/>
            <field name="class_id" ref="dim_class_grade_5"/>
            <field name="subject_id" ref="dim_subject_chinese"/>
            <field name="year_id" ref="dim_year_2026"/>
            <field name="version_id" ref="dim_version_pep"/>
            <field name="semester_id" ref="dim_semester_down"/>
            <field name="sequence">40</field>
        </record>
        <!-- 小学 五年级 数学 2026 人教版 下册 -->
        <record id="selector_g5_math_pep_down" model="learn.selector">
            <field name="category_id" ref="dim_category_nine_year"/>
            <field name="stage_id" ref="dim_stage_primary"/>
            <field name="class_id" ref="dim_class_grade_5"/>
            <field name="subject_id" ref="dim_subject_math"/>
            <field name="year_id" ref="dim_year_2026"/>
            <field name="version_id" ref="dim_version_pep"/>
            <field name="semester_id" ref="dim_semester_down"/>
            <field name="sequence">50</field>
        </record>

    </data>
</odoo>
